arxiv_summarizer/__init__.py
arxiv_summarizer/__main__.py
arxiv_summarizer/arxiv_wrapper.py
arxiv_summarizer/fetch_paper.py
arxiv_summarizer/summarizer.py
arxiv_summarizer/utils.py
arxiv_summarizer-0.1.1.dist-info/LICENSE
arxiv_summarizer-0.1.1.dist-info/METADATA
arxiv_summarizer-0.1.1.dist-info/WHEEL
arxiv_summarizer-0.1.1.dist-info/entry_points.txt
arxiv_summarizer-0.1.1.dist-info/top_level.txt
arxiv_summarizer-0.1.1.dist-info/RECORD
