Metadata-Version: 2.1
Name: arxiv-summarizer
Version: 0.1.1
Summary: A happy toolkit for arxiv paper summarization and understanding.
Home-page: https://github.com/ArchanGhosh/Arxiv-Summarizer
Author: Archan Ghosh, Arnav Das
Author-email: gharchan@gmail.com, arnav.das88@gmail.com
Maintainer: Archan Ghosh, Arnav Das, Debgandhar Ghosh, Subhayu Bala
Maintainer-email: gharchan@gmail.com, arnav.das88@gmail.com, debgandhar4000@gmail.com, balasubhayu99@gmail.com
License: Apache
Project-URL: GitHub, https://github.com/ArchanGhosh/Arxiv-Summarizer
Project-URL: Homepage, https://github.com/ArchanGhosh/Arxiv-Summarizer
Keywords: arxiv sdk summarization summary
Classifier: License :: OSI Approved :: Apache Software License
Classifier: Development Status :: 3 - Alpha
Classifier: Topic :: Communications
Classifier: Intended Audience :: Science/Research
Classifier: Operating System :: Microsoft :: Windows
Classifier: Operating System :: MacOS
Classifier: Operating System :: POSIX :: Linux
Classifier: Environment :: Console
Classifier: Environment :: GPU
Classifier: Programming Language :: Python :: 3.8
Classifier: Programming Language :: Python :: 3.9
Classifier: Programming Language :: Python :: 3.10
Classifier: Programming Language :: Python :: 3.11
License-File: LICENSE
Requires-Dist: langchain
Requires-Dist: arxiv
Requires-Dist: pymupdf
Requires-Dist: transformers
Requires-Dist: torch ==2.1.2
Requires-Dist: click
Requires-Dist: rich
Requires-Dist: pytest
Provides-Extra: dev
Requires-Dist: nox ; extra == 'dev'
Requires-Dist: pytest ; extra == 'dev'
Provides-Extra: docs
Requires-Dist: sphinx ; extra == 'docs'
Requires-Dist: sphinxemoji ; extra == 'docs'
Requires-Dist: pydata-sphinx-theme ; extra == 'docs'
Requires-Dist: numpydoc ; extra == 'docs'
Requires-Dist: sphinx-panels ; extra == 'docs'
Requires-Dist: matplotlib ; extra == 'docs'
Requires-Dist: Ipython ; extra == 'docs'
Requires-Dist: sphinx-hoverxref ; extra == 'docs'
